{
    "Application" : {
    },
    "MainWindow" : {
        "Parent" : "Application",
        "Window" : "#000000",
        "WindowText" : "#FFFFFF"
    },
    "MusicScrollBar" : {
        "Parent" : "MainWindow",
        "Base" : "#00000000",
        "Button" : "#FFFFFF00",
        "ButtonText" : "#FFFFFF"
    },
    "MusicStoreWidget" : {
        "Parent" : "MainWindow",
        "Window" : "#202020",
        "WindowText" : "#9D9D9D"
    },
    "MusicStoreActionButton" : {
        "Parent" : "MusicStoreWidget",
        "Button" : "#202020",
        "ButtonText" : "#9D9D9D"
    },
    "MusicStoreEmptyWidget" : {
        "Parent" : "MusicStoreWidget",
        "Window" : "#000000"
    },
    "MusicStoreDownloadList" : {
        "Parent" : "MusicStoreWidget",
        "Window" : "#202020"
    },
    "MusicStoreTitle" : {
        "Parent" : "MusicStoreWidget",
        "Window" : "#252525"
    },
    "MusicStoreTextLabel" :{
        "Parent" : "MusicStoreWidget",
        "WindowText" : "#FFFFFF"
    },
    "MusicStoreAlbumList" : {
        "Parent" : "MusicStoreWidget",
        "Base" : "#00000000",
        "Text" : "#FFFFFF"
    },
    "MusicStoreAlbumView" : {
        "Parent" : "MusicStoreAlbumList",
        "AlternateBase" : "#FFFFFF20",
        "Base" : "#00000000",
        "Window" : "#202020",
        "Text" : "#FFFFFF",
        "Button" : "#000000",
        "Highlight" : "#505050",
        "HighlightedText" : "#F7CF3D"
    },
    "NotificationView" : {
        "Parent" : "MainWindow",
        "Base" : "#00000000",
        "Window" : "#00000000",
        "Text" : "#616161",
        "Highlight" : "#F7CF3D",
        "HighlightedText" : "#616161"
    },
    "FileDialog" : {
        "Parent" : "MainWindow",
        "Base" : "#353535",
        "Window" : "#202020",
        "WindowText" : "#C0C0C0",
        "ToolTipBase" : "#202020",
        "ToolTipText" : "#C0C0C0",
        "Button" : "#202020",
        "ButtonText" : "#C0C0C0",
        "Text" : "#C0C0C0",
        "Highlight" : "#505050",
        "HighlightedText" : "#F7CF3D"
    },
    "LabelLineEdit" : {
        "Parent" : "Application",
        "Window" : "#000000",
        "Highlight" : "#C0C0C0",
        "HighlightedText" : "#000000"
    },
    "DownloadedLyricsListView" : {
        "Base" : "#00000000",
        "Window" : "#00000000",
        "Highlight" : "#cd8032",
        "HighlightedText" : "#FFFFFF"
    },
    "DownloadedLyricsPreview" : {
        "Parent" : "DownloadedLyricsListView",
        "Highlight" : "#cd8032",
        "Text" : "#333333"
    },
    "MusicAlbumView" : {
        "Parent" : "MainWindow",
        "Base" : "#303030",
        "Window" : "#303030",
        "Button" : "#FFFFFF00",
        "ButtonText" : "#FFFFFF",
        "Text" : "#FFFFFF",
        "Highlight" : "#606060",
        "HighlightedText" : "#f7cf3d"
    },
    "MusicDetailTooltip" : {
        "Parent" : "MainWindow",
        "Window" : "#FFFFFF",
        "WindowText" : "#FFFFFF"
    },
    "MusicSoloMenu" :{
        "Parent" : "MainWindow",
        "Base" : "#000000",
        "Window" : "#00000000",
        "WindowText" : "#FFFFFF",
        "Text" : "#FFFFFFFE",
        "Highlight" : "#606060",
        "HighlightedText" : "#f7cf3d"
    },
    "MusicMultiMenu" : {
        "Parent" : "MusicSoloMenu"
    },
    "CategoryDisplayTreeView" : {
        "Parent" : "MainWindow",
        "Base" : "#00000000",
        "AlternateBase" : "#FFFFFF20",
        "Window" : "#202020",
        "Text" : "#FFFFFF",
        "Button" : "#000000",
        "Highlight" : "#505050",
        "HighlightedText" : "#F7CF3D"
    },
    "MusicAlbumTitleLabel" : {
        "Parent" : "MainWindow",
        "WindowText" : "#000000"
    },
    "MusicAlbumDetailLabel" : {
        "Parent" : "MainWindow",
        "WindowText" : "#0000009A"
    },
    "LibraryEmptyHint" : {
        "Parent" : "MainWindow",
        "Window" : "#353535",
        "WindowText" : "#A0A0A0"
    },
    "LibraryEmptyHintLabel" : {
        "Parent" : "LibraryEmptyHint"
    },
    "LibraryTreeView" : {
        "Parent" : "MainWindow",
        "AlternateBase" : "#FFFFFF20",
        "Base" : "#202020",
        "Window" : "#202020",
        "Text" : "#FFFFFF",
        "Button" : "#000000",
        "Highlight" : "#505050",
        "HighlightedText" : "#F7CF3D"
    },
    "MusicTreeViewHeaderMenu" : {
        "Parent" : "MainWindow",
        "Base" : "#00000000",
        "Window" : "#00000000",
        "WindowText" : "#FFFFFF",
        "Text" : "#FFFFFFFE",
        "Highlight" : "#606060",
        "HighlightedText" : "#f7cf3d"
    },
    "HeaderLyrics" : {
        "Parent" : "MainWindow",
        "Text" : "#646464",
        "Highlight" : "#f7cf3d"
    },
    "MiniLyrics" : {
        "Parent" : "HeaderLyrics"
    },
    "HeaderPlayerLabel" : {
        "Parent" : "MainWindow",
        "WindowText" : "#FFFFFF",
        "Base" : "#000000",
        "Text" : "#FFFFFFFE",
        "Highlight" : "#606060",
        "HighlightedText" : "#f7cf3d"
    },
    "MiniPlayer" : {
        "Parent" : "MainWindow",
        "MainWindow" : "#000000"
    },
    "MiniPosition" : {
        "Parent" : "MiniPlayer",
        "Base" : "#000000",
        "WindowText" : "#AAAAAA",
        "Text" : "#FFFFFF",
        "Highlight" : "#606060",
        "HighlightedText" : "#f7cf3d"
    },
    "MainPlayer" : {
        "Parent" : "MainWindow",
        "MainWindow" : "#000000"
    },
    "NowPlayingListView" : {
        "Parent" : "MainPlayer",
        "Base" : "#00000000",
        "Highlight" : "#505050",
        "HighlightedText" : "#F7CF3D"
    },
    "MainPlayerLabel" : {
        "Parent" : "MainPlayer",
        "WindowText" : "#FFFFFF",
        "Base" : "#000000",
        "Text" : "#FFFFFFFE",
        "Highlight" : "#606060",
        "HighlightedText" : "#f7cf3d"
    },
    "MainPlayerInfoPanel" :{
        "Parent" : "MainPlayerLabel",
        "WindowText" : "#A0A0A0",
        "Text" : "#FFFFFF54",
        "Highlight" : "#f7cf3d"
    },
    "MainPlayerLyrics" : {
        "Parent" : "MainPlayerInfoPanel"
    },
    "SearchBox" : {
        "Parent" : "MainWindow",
        "Base" : "#000000",
        "Highlight" : "#F7CF3D",
        "HighlightedText" : "#000000"
    },
    "MouseSenseHeader" : {
        "Parent" : "MainWindow",
        "Base" : "#00000000",
        "Window" : "#FFFFFF00"
    },
    "MusicTreeViewHeaderMenu" : {
        "Parent" : "MouseSenseHeader",
        "Base" : "#00000000",
        "Window" : "#00000000",
        "WindowText" : "#FFFFFF",
        "Text" : "#FFFFFFFE",
        "Highlight" : "#606060",
        "HighlightedText" : "#f7cf3d"
    },
    "PlaylistTreeView" :{
        "Parent" : "MainWindow",
        "AlternateBase" : "#FFFFFF20",
        "Base" : "#202020",
        "Window" : "#202020",
        "Text" : "#FFFFFF",
        "Button" : "#000000",
        "Highlight" : "#505050",
        "HighlightedText" : "#F7CF3D"
    },
    "CategoryInformationContainer" : {
        "Parent" : "MainWindowHeader"
    },
    "CategoryViewerLabel" : {
        "Parent" : "CategoryInformationContainer",
        "WindowText" : "#FFFFFF"
    },
    "CategoryDetailLabel" : {
        "Parent" : "CategoryInformationContainer",
        "WindowText" : "#FFFFFFA0"
    },
    "CategoryListViewBase" : {
        "Parent" : "MainWindow",
        "Base" : "#FFFFFF",
        "Window" : "#303030",
        "Button" : "#303030",
        "Text" : "#8F8F8FAF",
        "Highlight" : "#FFFFFF40",
        "HighlightedText" : "#F7CF3D"
    },
    "MusicCategorySearch" : {
        "Parent" : "CategoryListViewBase",
        "Button" : "#303030",
        "ButtonText" : "#AAAAAA"
    },
    "AlbumListView" : {
        "Parent" : "MainWindow",
        "Base" : "#00000000",
        "WindowText" : "#000000",
        "Text" : "#000000",
        "Button": "#00000000",
        "Highlight" : "#f7cf3d",
        "HighlightedText" : "#000000"
    },
    "PlaylistInformationContainer" : {
        "Parent" : "MainWindowHeader"
    },
    "PlaylistViewerLabel" : {
        "Parent" : "PlaylistInformationContainer",
        "WindowText" : "#FFFFFF"
    },
    "PlaylistDetailLabel" : {
        "Parent" : "PlaylistInformationContainer",
        "WindowText" : "#FFFFFFA0"
    },
    "PlaylistEmptyHint" : {
        "Parent" : "MainWindow",
        "Window" : "#353535",
        "WindowText" : "#A0A0A0"
    },
    "PlaylistEmptyHintLabel" : {
        "Parent" : "PlaylistEmptyHint",
        "WindowText" : "#A0A0A0"
    },
    "PlaylistListDelegateEditor" : {
        "Parent" : "PlaylistEmptyHint",
        "Base" : "#505050",
        "Window" : "#ff303030",
        "WindowText" : "#00000000",
        "Button" : "#00000000",
        "Text" : "#c6c6c6",
        "Highlight" : "#ffffff40",
        "HighlightedText" : "#f7cf3d"
    },
    "PlaylistListEditorMenu" : {
        "Parent" : "PlaylistEmptyHint",
        "Base" : "#000000",
        "Window" : "#000000",
        "WindowText" : "#FFFFFF",
        "Text" : "#FFFFFFFE",
        "Highlight" : "#606060",
        "HighlightedText" : "#F7CF3D"
    },
    "CategoryTabBar" : {
        "Parent" : "MainWindow",
        "Window" : "#FFFFFF"
    },
    "CategoryTab" : {
        "Parent" : "MainWindow",
        "Button" : "#000000",
        "ButtonText" : "#FFFFFF"
    },
    "MainWindowHeader" :
    {
        "Parent" : "MainWindow",
        "Window" : "#101010",
        "Text" : "#9F9F9F"
    },
    "MainWindowButtonText" :
    {
        "Parent" : "MainWindowHeader",
        "ButtonText" : "#FFFFFF"
    },
    "Preference" :
    {
        "Parent" : "MainWindow",
        "Window" : "#1e1e1e"
    },
    "PreferenceContent" :
    {
        "Parent" : "Preference",
        "Window" : "#2A2A2A"
    },
    "PreferenceAboutLabel" :
    {
        "Parent" : "PreferenceContent",
        "WindowText" : "#A0A0A0"
    },
    "PreferenceAboutCopyright" :
    {
        "Parent" : "PreferenceContent",
        "Base" : "#00000000",
        "Text" : "#A0A0A0",
        "Highlight" : "#00000000",
        "HighlightedText" : "#A0A0A0"
    },
    "PreferenceLanguagePanelItem" :
    {
        "Parent" : "PreferenceContent",
        "Highlight" : "#606060",
        "HighlightedText" : "#F7CF3D"
    },
    "PreferenceSidebar" :
    {
        "Parent" : "Preference"
    },
    "PreferenceItem" :
    {
        "Parent" : "PreferenceSidebar",
        "Button" : "#444444",
        "ButtonText" : "#F7CF3D"
    },
    "PreferenceSidebarBottom" :
    {
        "Parent" : "PreferenceSidebar"
    },
    "PreferenceTitleBar" :
    {
        "Parent" : "PreferenceSidebar"
    },
    "PreferenceTitleBarLabel" :
    {
        "Parent" : "PreferenceTitleBar",
        "WindowText" : "#FFFFFF"
    },
    "PreferenceHeaderButton" :
    {
        "Parent" : "PreferenceTitleBar",
        "Window" : "#000000"
    }
}
